setup.py
static_bhp/__init__.py
static_bhp/static_bhp.py
static_bhp.egg-info/PKG-INFO
static_bhp.egg-info/SOURCES.txt
static_bhp.egg-info/dependency_links.txt
static_bhp.egg-info/not-zip-safe
static_bhp.egg-info/top_level.txt