Metadata-Version: 2.1
Name: static-bhp
Version: 1.2.0
Summary: README.md
Home-page: UNKNOWN
Author: Betini Akarandut
Author-email: betiniakarandut@gmail.com
License: UNKNOWN
Platform: UNKNOWN
